nnk_unzip/__init__.py
nnk_unzip/__main__.py
nnk_unzip-0.1.0.dist-info/licenses/LICENSE
nnk_unzip-0.1.0.dist-info/METADATA
nnk_unzip-0.1.0.dist-info/WHEEL
nnk_unzip-0.1.0.dist-info/entry_points.txt
nnk_unzip-0.1.0.dist-info/top_level.txt
nnk_unzip-0.1.0.dist-info/RECORD
