Metadata-Version: 2.4
Name: nnk-unzip
Version: 0.1.0
License-File: LICENSE
Requires-Dist: questionary
Dynamic: license-file
Dynamic: requires-dist
